primitive_pal-0.1.4.dist-info/METADATA
primitive_pal-0.1.4.dist-info/WHEEL
primitive_pal/__init__.py
primitive_pal/primitive_pal.cpython-310-x86_64-linux-gnu.so
primitive_pal-0.1.4.dist-info/RECORD
